[
  {
    "country": "AI",
    "name": ".ANGUILLA",
    "function": [],
    "coordinates": {
      "lat": 0,
      "lon": 0
    }
  },
  {
    "country": "AI",
    "location": "AXA",
    "name": "Anguilla",
    "nameWoDiacritics": "Anguilla",
    "status": "AI",
    "function": [
      3,
      4
    ],
    "date": 9601,
    "coordinates": {
      "lat": 0,
      "lon": 0
    }
  },
  {
    "country": "AI",
    "location": "BLP",
    "name": "Blowing Point",
    "nameWoDiacritics": "Blowing Point",
    "status": "QQ",
    "function": [
      0
    ],
    "date": 8110,
    "coordinates": {
      "lat": 0,
      "lon": 0
    }
  },
  {
    "country": "AI",
    "location": "CRH",
    "name": "Crocus Hill",
    "nameWoDiacritics": "Crocus Hill",
    "status": "RL",
    "function": [
      2
    ],
    "date": 607,
    "coordinates": {
      "lat": 18.216666666666665,
      "lon": 6.5
    }
  },
  {
    "country": "AI",
    "location": "MBB",
    "name": "Meads Bay Beach",
    "nameWoDiacritics": "Meads Bay Beach",
    "status": "RL",
    "function": [
      0
    ],
    "date": 1601,
    "coordinates": {
      "lat": 18.166666666666668,
      "lon": 6.5
    }
  },
  {
    "country": "AI",
    "location": "RBY",
    "name": "Road Bay",
    "nameWoDiacritics": "Road Bay",
    "status": "RL",
    "function": [
      2
    ],
    "date": 1,
    "coordinates": {
      "lat": 0,
      "lon": 0
    }
  },
  {
    "country": "AI",
    "location": "SOM",
    "name": "Sombrero",
    "nameWoDiacritics": "Sombrero",
    "status": "RQ",
    "function": [
      0
    ],
    "date": 901,
    "coordinates": {
      "lat": 18.6,
      "lon": 6.533333333333333
    }
  },
  {
    "country": "AI",
    "location": "FOR",
    "name": "The Forest",
    "nameWoDiacritics": "The Forest",
    "status": "QQ",
    "function": [
      0
    ],
    "date": 8110,
    "coordinates": {
      "lat": 0,
      "lon": 0
    }
  },
  {
    "country": "AI",
    "location": "ROA",
    "name": "The Road",
    "nameWoDiacritics": "The Road",
    "status": "QQ",
    "function": [
      0
    ],
    "date": 8110,
    "coordinates": {
      "lat": 0,
      "lon": 0
    }
  },
  {
    "country": "AI",
    "location": "VAL",
    "name": "The Valley",
    "nameWoDiacritics": "The Valley",
    "status": "RL",
    "function": [
      2
    ],
    "date": 201,
    "coordinates": {
      "lat": 18.216666666666665,
      "lon": 6.5
    }
  },
  {
    "country": "AI",
    "location": "WLL",
    "name": "Wall Blake",
    "nameWoDiacritics": "Wall Blake",
    "status": "RL",
    "function": [
      0,
      3
    ],
    "date": 201,
    "coordinates": {
      "lat": 0,
      "lon": 0
    }
  }
]