[
  {
    "country": "BJ",
    "name": ".BENIN",
    "function": [],
    "coordinates": {
      "lat": 0,
      "lon": 0
    }
  },
  {
    "country": "BJ",
    "location": "AMV",
    "name": "Abomey-Calavi",
    "nameWoDiacritics": "Abomey-Calavi",
    "subdivision": "AQ",
    "status": "RL",
    "function": [
      2
    ],
    "date": 1407,
    "coordinates": {
      "lat": 6.45,
      "lon": 0.36666666666666664
    }
  },
  {
    "country": "BJ",
    "location": "AGT",
    "name": "Agbanta",
    "nameWoDiacritics": "Agbanta",
    "status": "RL",
    "function": [
      2
    ],
    "date": 407,
    "coordinates": {
      "lat": 6.616666666666667,
      "lon": 0.36666666666666664
    }
  },
  {
    "country": "BJ",
    "location": "BOH",
    "name": "Bohicon",
    "nameWoDiacritics": "Bohicon",
    "status": "RL",
    "function": [
      1,
      2
    ],
    "date": 307,
    "coordinates": {
      "lat": 7.2,
      "lon": 0.3333333333333333
    }
  },
  {
    "country": "BJ",
    "location": "COO",
    "name": "Cotonou",
    "nameWoDiacritics": "Cotonou",
    "status": "AI",
    "function": [
      0,
      3,
      4
    ],
    "date": 9601,
    "coordinates": {
      "lat": 0,
      "lon": 0
    }
  },
  {
    "country": "BJ",
    "location": "DDJ",
    "name": "Djidja",
    "nameWoDiacritics": "Djidja",
    "subdivision": "ZO",
    "status": "RL",
    "function": [
      2
    ],
    "date": 1807,
    "coordinates": {
      "lat": 7.333333333333333,
      "lon": 0.25
    }
  },
  {
    "country": "BJ",
    "location": "DJA",
    "name": "Djougou",
    "nameWoDiacritics": "Djougou",
    "status": "AI",
    "function": [
      3
    ],
    "date": 9912,
    "coordinates": {
      "lat": 0,
      "lon": 0
    }
  },
  {
    "country": "BJ",
    "location": "GLA",
    "name": "GlazouÈ",
    "nameWoDiacritics": "Glazoue",
    "status": "RL",
    "function": [
      1,
      2
    ],
    "date": 307,
    "coordinates": {
      "lat": 7.966666666666667,
      "lon": 0.35
    }
  },
  {
    "country": "BJ",
    "location": "KDC",
    "name": "Kandi",
    "nameWoDiacritics": "Kandi",
    "status": "AI",
    "function": [
      3
    ],
    "date": 9912,
    "coordinates": {
      "lat": 0,
      "lon": 0
    }
  },
  {
    "country": "BJ",
    "location": "LKS",
    "name": "Lokossa",
    "nameWoDiacritics": "Lokossa",
    "subdivision": "MO",
    "status": "RL",
    "function": [
      2
    ],
    "date": 1101,
    "coordinates": {
      "lat": 6.633333333333333,
      "lon": 0.23333333333333334
    }
  },
  {
    "country": "BJ",
    "location": "NAE",
    "name": "Natitingou",
    "nameWoDiacritics": "Natitingou",
    "status": "AI",
    "function": [
      3
    ],
    "date": 9912,
    "coordinates": {
      "lat": 0,
      "lon": 0
    }
  },
  {
    "country": "BJ",
    "location": "DA3",
    "name": "Ndali",
    "nameWoDiacritics": "Ndali",
    "subdivision": "BO",
    "status": "RL",
    "function": [
      2
    ],
    "date": 1701,
    "coordinates": {
      "lat": 9.85,
      "lon": 0.4
    }
  },
  {
    "country": "BJ",
    "location": "OIH",
    "name": "Ouidah",
    "nameWoDiacritics": "Ouidah",
    "subdivision": "AQ",
    "status": "RL",
    "function": [
      2
    ],
    "date": 1407,
    "coordinates": {
      "lat": 6.366666666666666,
      "lon": 0.3333333333333333
    }
  },
  {
    "country": "BJ",
    "location": "PKO",
    "name": "Parakou",
    "nameWoDiacritics": "Parakou",
    "status": "AI",
    "function": [
      3
    ],
    "date": 9912,
    "coordinates": {
      "lat": 0,
      "lon": 0
    }
  },
  {
    "country": "BJ",
    "location": "PTN",
    "name": "Porto-Novo",
    "nameWoDiacritics": "Porto-Novo",
    "subdivision": "OU",
    "status": "RL",
    "function": [
      0,
      1,
      2
    ],
    "date": 401,
    "coordinates": {
      "lat": 6.483333333333333,
      "lon": 0.38333333333333336
    }
  },
  {
    "country": "BJ",
    "location": "SVF",
    "name": "SavÈ",
    "nameWoDiacritics": "Save",
    "status": "AI",
    "function": [
      3
    ],
    "date": 212,
    "coordinates": {
      "lat": 8.033333333333333,
      "lon": 0.36666666666666664
    }
  },
  {
    "country": "BJ",
    "location": "SEM",
    "name": "Seme Terminal",
    "nameWoDiacritics": "Seme Terminal",
    "status": "RQ",
    "function": [
      0
    ],
    "date": 9506,
    "coordinates": {
      "lat": 0,
      "lon": 0
    }
  },
  {
    "country": "BJ",
    "location": "TAN",
    "name": "TanguiÈta",
    "nameWoDiacritics": "Tanguieta",
    "status": "RL",
    "function": [
      2
    ],
    "date": 607,
    "coordinates": {
      "lat": 10.616666666666667,
      "lon": 0.18333333333333332
    }
  }
]