[
  {
    "change": "",
    "country": "LI",
    "location": "",
    "name": ".LIECHTENSTEIN",
    "nameWoDiacritics": "",
    "subdivision": "",
    "status": "",
    "function": "",
    "date": "",
    "iata": "",
    "coordinates": "",
    "remarks": ""
  },
  {
    "change": "",
    "country": "LI",
    "location": "BAZ",
    "name": "Balzers",
    "nameWoDiacritics": "Balzers",
    "subdivision": "",
    "status": "RL",
    "function": "--3-----",
    "date": "0601",
    "iata": "",
    "coordinates": "4704N 00930E",
    "remarks": ""
  },
  {
    "change": "",
    "country": "LI",
    "location": "ESC",
    "name": "Eschen",
    "nameWoDiacritics": "Eschen",
    "subdivision": "",
    "status": "RL",
    "function": "--3-----",
    "date": "0901",
    "iata": "",
    "coordinates": "4712N 00931E",
    "remarks": ""
  },
  {
    "change": "",
    "country": "LI",
    "location": "GAM",
    "name": "Gamprin-Bendern",
    "nameWoDiacritics": "Gamprin-Bendern",
    "subdivision": "",
    "status": "RL",
    "function": "--3-----",
    "date": "1107",
    "iata": "",
    "coordinates": "",
    "remarks": ""
  },
  {
    "change": "",
    "country": "LI",
    "location": "MAU",
    "name": "Mauren",
    "nameWoDiacritics": "Mauren",
    "subdivision": "",
    "status": "RQ",
    "function": "--3-----",
    "date": "1001",
    "iata": "",
    "coordinates": "4713N 00932E",
    "remarks": ""
  },
  {
    "change": "",
    "country": "LI",
    "location": "NEN",
    "name": "Nendeln",
    "nameWoDiacritics": "Nendeln",
    "subdivision": "01",
    "status": "RL",
    "function": "--3-----",
    "date": "1707",
    "iata": "",
    "coordinates": "4712N 00933E",
    "remarks": ""
  },
  {
    "change": "",
    "country": "LI",
    "location": "PLK",
    "name": "Planken",
    "nameWoDiacritics": "Planken",
    "subdivision": "05",
    "status": "RL",
    "function": "--3-----",
    "date": "1307",
    "iata": "",
    "coordinates": "4711N 00932E",
    "remarks": ""
  },
  {
    "change": "",
    "country": "LI",
    "location": "RGL",
    "name": "Ruggell",
    "nameWoDiacritics": "Ruggell",
    "subdivision": "",
    "status": "RL",
    "function": "--3-----",
    "date": "0407",
    "iata": "",
    "coordinates": "4714N 00931E",
    "remarks": ""
  },
  {
    "change": "",
    "country": "LI",
    "location": "SCN",
    "name": "Schaan",
    "nameWoDiacritics": "Schaan",
    "subdivision": "",
    "status": "RL",
    "function": "-23-----",
    "date": "0601",
    "iata": "",
    "coordinates": "4710N 00930E",
    "remarks": ""
  },
  {
    "change": "",
    "country": "LI",
    "location": "SCH",
    "name": "Schaanwald",
    "nameWoDiacritics": "Schaanwald",
    "subdivision": "",
    "status": "RL",
    "function": "--3----B",
    "date": "0501",
    "iata": "",
    "coordinates": "4713N 00934E",
    "remarks": ""
  },
  {
    "change": "",
    "country": "LI",
    "location": "TES",
    "name": "Triesen",
    "nameWoDiacritics": "Triesen",
    "subdivision": "",
    "status": "RQ",
    "function": "--3-----",
    "date": "9705",
    "iata": "QVU",
    "coordinates": "",
    "remarks": ""
  },
  {
    "change": "",
    "country": "LI",
    "location": "VDZ",
    "name": "Vaduz",
    "nameWoDiacritics": "Vaduz",
    "subdivision": "",
    "status": "RL",
    "function": "--3-----",
    "date": "0201",
    "iata": "",
    "coordinates": "4709N 00932E",
    "remarks": ""
  }
]